{"paging":{"pageIndex":1,"pageSize":500,"total":57},"baseComponent":{"id":"AYpN4tr29hjvw5R4pm0K","key":"fga-eps-mds_2023.2-Dnit-UpsService","name":"2023.2-Dnit-UpsService","qualifier":"TRK","measures":[{"metric":"comment_lines_density","value":"0.1","bestValue":false},{"metric":"complexity","value":"242"},{"metric":"coverage","value":"89.9","bestValue":false},{"metric":"duplicated_lines_density","value":"0.0","bestValue":true},{"metric":"files","value":"29"},{"metric":"functions","value":"207"},{"metric":"ncloc","value":"902"},{"metric":"security_rating","value":"1.0","bestValue":true},{"metric":"test_errors","value":"0","bestValue":true},{"metric":"test_execution_time","value":"2526"},{"metric":"test_failures","value":"0","bestValue":true},{"metric":"tests","value":"25"}]},"components":[{"id":"AYtQFh_ZlVtF5-wq_4-B","key":"fga-eps-mds_2023.2-Dnit-UpsService:api","name":"api","qualifier":"DIR","path":"api","measures":[{"metric":"comment_lines_density","value":"0.0","bestValue":false},{"metric":"complexity","value":"77"},{"metric":"coverage","value":"95.7","bestValue":false},{"metric":"duplicated_lines_density","value":"0.0","bestValue":true},{"metric":"files","value":"5"},{"metric":"functions","value":"77"},{"metric":"ncloc","value":"160"},{"metric":"security_rating","value":"1.0","bestValue":true}]},{"id":"AYtQFh_ZlVtF5-wq_49h","key":"fga-eps-mds_2023.2-Dnit-UpsService:app/Services/ApiException.cs","name":"ApiException.cs","qualifier":"FIL","path":"app/Services/ApiException.cs","language":"cs","measures":[{"metric":"comment_lines_density","value":"0.0","bestValue":false},{"metric":"complexity","value":"20"},{"metric":"coverage","value":"40.0","bestValue":false},{"metric":"files","value":"1"},{"metric":"functions","value":"13"},{"metric":"ncloc","value":"71"},{"metric":"security_rating","value":"1.0","bestValue":true},{"metric":"duplicated_lines_density","value":"0.0","bestValue":true},{"metric":"test_failures","value":"0","bestValue":true},{"metric":"test_errors","value":"0","bestValue":true}]},{"id":"AYpN5P0PgIp5pWdLoPus","key":"fga-eps-mds_2023.2-Dnit-UpsService:app","name":"app","qualifier":"DIR","path":"app","measures":[{"metric":"comment_lines_density","value":"0.1","bestValue":false},{"metric":"complexity","value":"165"},{"metric":"coverage","value":"89.1","bestValue":false},{"metric":"duplicated_lines_density","value":"0.0","bestValue":true},{"metric":"files","value":"24"},{"metric":"functions","value":"130"},{"metric":"ncloc","value":"742"},{"metric":"security_rating","value":"1.0","bestValue":true}]},{"id":"AYtaLshNBGTqb9CCn3yp","key":"fga-eps-mds_2023.2-Dnit-UpsService:app/Services/AppController.cs","name":"AppController.cs","qualifier":"FIL","path":"app/Services/AppController.cs","language":"cs","measures":[{"metric":"comment_lines_density","value":"0.0","bestValue":false},{"metric":"complexity","value":"4"},{"metric":"coverage","value":"100.0","bestValue":true},{"metric":"files","value":"1"},{"metric":"functions","value":"3"},{"metric":"ncloc","value":"10"},{"metric":"security_rating","value":"1.0","bestValue":true},{"metric":"duplicated_lines_density","value":"0.0","bestValue":true},{"metric":"test_failures","value":"0","bestValue":true},{"metric":"test_errors","value":"0","bestValue":true}]},{"id":"AYtQFh_ZlVtF5-wq_49l","key":"fga-eps-mds_2023.2-Dnit-UpsService:app/Entidades/AppDbContext.cs","name":"AppDbContext.cs","qualifier":"FIL","path":"app/Entidades/AppDbContext.cs","language":"cs","measures":[{"metric":"comment_lines_density","value":"0.0","bestValue":false},{"metric":"complexity","value":"5"},{"metric":"coverage","value":"100.0","bestValue":true},{"metric":"files","value":"1"},{"metric":"functions","value":"5"},{"metric":"ncloc","value":"12"},{"metric":"security_rating","value":"1.0","bestValue":true},{"metric":"duplicated_lines_density","value":"0.0","bestValue":true},{"metric":"test_failures","value":"0","bestValue":true},{"metric":"test_errors","value":"0","bestValue":true}]},{"id":"AYtQFh_ZlVtF5-wq_491","key":"fga-eps-mds_2023.2-Dnit-UpsService:test/Stub/AppDbContextExtensions.cs","name":"AppDbContextExtensions.cs","qualifier":"UTS","path":"test/Stub/AppDbContextExtensions.cs","language":"cs","measures":[{"metric":"security_rating","value":"1.0","bestValue":true},{"metric":"duplicated_lines_density","value":"0.0","bestValue":true},{"metric":"test_failures","value":"0","bestValue":true},{"metric":"test_errors","value":"0","bestValue":true}]},{"id":"AYpN5P0PgIp5pWdLoPun","key":"fga-eps-mds_2023.2-Dnit-UpsService:app/appsettings.Development.json","name":"appsettings.Development.json","qualifier":"FIL","path":"app/appsettings.Development.json","language":"json","measures":[{"metric":"files","value":"1"},{"metric":"security_rating","value":"1.0","bestValue":true},{"metric":"duplicated_lines_density","value":"0.0","bestValue":true},{"metric":"test_failures","value":"0","bestValue":true},{"metric":"test_errors","value":"0","bestValue":true}]},{"id":"AYpN5P0PgIp5pWdLoPuq","key":"fga-eps-mds_2023.2-Dnit-UpsService:app/appsettings.json","name":"appsettings.json","qualifier":"FIL","path":"app/appsettings.json","language":"json","measures":[{"metric":"files","value":"1"},{"metric":"security_rating","value":"1.0","bestValue":true},{"metric":"duplicated_lines_density","value":"0.0","bestValue":true},{"metric":"test_failures","value":"0","bestValue":true},{"metric":"test_errors","value":"0","bestValue":true}]},{"id":"AYtaLshNBGTqb9CCn3yq","key":"fga-eps-mds_2023.2-Dnit-UpsService:app/appsettings.Test.json","name":"appsettings.Test.json","qualifier":"FIL","path":"app/appsettings.Test.json","language":"json","measures":[{"metric":"files","value":"1"},{"metric":"security_rating","value":"1.0","bestValue":true},{"metric":"duplicated_lines_density","value":"0.0","bestValue":true},{"metric":"test_failures","value":"0","bestValue":true},{"metric":"test_errors","value":"0","bestValue":true}]},{"id":"AYtaLshNBGTqb9CCn3yo","key":"fga-eps-mds_2023.2-Dnit-UpsService:test/Fixtures/AuthTest.cs","name":"AuthTest.cs","qualifier":"UTS","path":"test/Fixtures/AuthTest.cs","language":"cs","measures":[{"metric":"security_rating","value":"1.0","bestValue":true},{"metric":"duplicated_lines_density","value":"0.0","bestValue":true},{"metric":"test_failures","value":"0","bestValue":true},{"metric":"test_errors","value":"0","bestValue":true}]},{"id":"AYtQFh_ZlVtF5-wq_494","key":"fga-eps-mds_2023.2-Dnit-UpsService:test/Fixtures/Base.cs","name":"Base.cs","qualifier":"UTS","path":"test/Fixtures/Base.cs","language":"cs","measures":[{"metric":"security_rating","value":"1.0","bestValue":true},{"metric":"duplicated_lines_density","value":"0.0","bestValue":true},{"metric":"test_failures","value":"0","bestValue":true},{"metric":"test_errors","value":"0","bestValue":true}]},{"id":"AYpN5P0PgIp5pWdLoPum","key":"fga-eps-mds_2023.2-Dnit-UpsService:app/Controllers","name":"Controllers","qualifier":"DIR","path":"app/Controllers","measures":[{"metric":"comment_lines_density","value":"0.0","bestValue":false},{"metric":"complexity","value":"16"},{"metric":"coverage","value":"96.3","bestValue":false},{"metric":"duplicated_lines_density","value":"0.0","bestValue":true},{"metric":"files","value":"3"},{"metric":"functions","value":"7"},{"metric":"ncloc","value":"150"},{"metric":"security_rating","value":"1.0","bestValue":true}]},{"id":"AYtQFh_ZlVtF5-wq_49z","key":"fga-eps-mds_2023.2-Dnit-UpsService:app/Dominio","name":"Dominio","qualifier":"DIR","path":"app/Dominio","measures":[{"metric":"comment_lines_density","value":"0.0","bestValue":false},{"metric":"complexity","value":"17"},{"metric":"coverage","value":"100.0","bestValue":true},{"metric":"duplicated_lines_density","value":"0.0","bestValue":true},{"metric":"files","value":"2"},{"metric":"functions","value":"17"},{"metric":"ncloc","value":"24"},{"metric":"security_rating","value":"1.0","bestValue":true}]},{"id":"AYtQFh_ZlVtF5-wq_49o","key":"fga-eps-mds_2023.2-Dnit-UpsService:app/Entidades","name":"Entidades","qualifier":"DIR","path":"app/Entidades","measures":[{"metric":"comment_lines_density","value":"0.0","bestValue":false},{"metric":"complexity","value":"76"},{"metric":"coverage","value":"98.2","bestValue":false},{"metric":"duplicated_lines_density","value":"0.0","bestValue":true},{"metric":"files","value":"3"},{"metric":"functions","value":"72"},{"metric":"ncloc","value":"108"},{"metric":"security_rating","value":"1.0","bestValue":true}]},{"id":"AYtQFh_ZlVtF5-wq_499","key":"fga-eps-mds_2023.2-Dnit-UpsService:api/Enums.cs","name":"Enums.cs","qualifier":"FIL","path":"api/Enums.cs","language":"cs","measures":[{"metric":"comment_lines_density","value":"0.0","bestValue":false},{"metric":"complexity","value":"0"},{"metric":"files","value":"1"},{"metric":"functions","value":"0"},{"metric":"ncloc","value":"88"},{"metric":"security_rating","value":"1.0","bestValue":true},{"metric":"duplicated_lines_density","value":"0.0","bestValue":true},{"metric":"test_failures","value":"0","bestValue":true},{"metric":"test_errors","value":"0","bestValue":true}]},{"id":"AYtQFh_ZlVtF5-wq_49x","key":"fga-eps-mds_2023.2-Dnit-UpsService:app/Dominio/Escola.cs","name":"Escola.cs","qualifier":"FIL","path":"app/Dominio/Escola.cs","language":"cs","measures":[{"metric":"comment_lines_density","value":"0.0","bestValue":false},{"metric":"complexity","value":"4"},{"metric":"coverage","value":"100.0","bestValue":true},{"metric":"files","value":"1"},{"metric":"functions","value":"4"},{"metric":"ncloc","value":"8"},{"metric":"security_rating","value":"1.0","bestValue":true},{"metric":"duplicated_lines_density","value":"0.0","bestValue":true},{"metric":"test_failures","value":"0","bestValue":true},{"metric":"test_errors","value":"0","bestValue":true}]},{"id":"AYtQFh_ZlVtF5-wq_495","key":"fga-eps-mds_2023.2-Dnit-UpsService:test/Fixtures","name":"Fixtures","qualifier":"DIR","path":"test/Fixtures","measures":[{"metric":"security_rating","value":"1.0","bestValue":true}]},{"id":"AYtQFh_ZlVtF5-wq_49f","key":"fga-eps-mds_2023.2-Dnit-UpsService:app/Services/Interfaces","name":"Interfaces","qualifier":"DIR","path":"app/Services/Interfaces","measures":[{"metric":"comment_lines_density","value":"0.0","bestValue":false},{"metric":"complexity","value":"0"},{"metric":"duplicated_lines_density","value":"0.0","bestValue":true},{"metric":"files","value":"3"},{"metric":"functions","value":"0"},{"metric":"ncloc","value":"30"},{"metric":"security_rating","value":"1.0","bestValue":true}]},{"id":"AYtQFh_ZlVtF5-wq_49r","key":"fga-eps-mds_2023.2-Dnit-UpsService:app/Repositorio/Interfaces","name":"Interfaces","qualifier":"DIR","path":"app/Repositorio/Interfaces","measures":[{"metric":"comment_lines_density","value":"0.0","bestValue":false},{"metric":"complexity","value":"0"},{"metric":"duplicated_lines_density","value":"0.0","bestValue":true},{"metric":"files","value":"2"},{"metric":"functions","value":"0"},{"metric":"ncloc","value":"21"},{"metric":"security_rating","value":"1.0","bestValue":true}]},{"id":"AYtQFh_ZlVtF5-wq_49q","key":"fga-eps-mds_2023.2-Dnit-UpsService:app/Repositorio/Interfaces/IRodoviaRepositorio.cs","name":"IRodoviaRepositorio.cs","qualifier":"FIL","path":"app/Repositorio/Interfaces/IRodoviaRepositorio.cs","language":"cs","measures":[{"metric":"comment_lines_density","value":"0.0","bestValue":false},{"metric":"complexity","value":"0"},{"metric":"files","value":"1"},{"metric":"functions","value":"0"},{"metric":"ncloc","value":"9"},{"metric":"security_rating","value":"1.0","bestValue":true},{"metric":"duplicated_lines_density","value":"0.0","bestValue":true},{"metric":"test_failures","value":"0","bestValue":true},{"metric":"test_errors","value":"0","bestValue":true}]},{"id":"AYtQFh_ZlVtF5-wq_49e","key":"fga-eps-mds_2023.2-Dnit-UpsService:app/Services/Interfaces/IRodoviaService.cs","name":"IRodoviaService.cs","qualifier":"FIL","path":"app/Services/Interfaces/IRodoviaService.cs","language":"cs","measures":[{"metric":"comment_lines_density","value":"0.0","bestValue":false},{"metric":"complexity","value":"0"},{"metric":"files","value":"1"},{"metric":"functions","value":"0"},{"metric":"ncloc","value":"8"},{"metric":"security_rating","value":"1.0","bestValue":true},{"metric":"duplicated_lines_density","value":"0.0","bestValue":true},{"metric":"test_failures","value":"0","bestValue":true},{"metric":"test_errors","value":"0","bestValue":true}]},{"id":"AYtQFh_ZlVtF5-wq_49p","key":"fga-eps-mds_2023.2-Dnit-UpsService:app/Repositorio/Interfaces/ISinistroRepositorio.cs","name":"ISinistroRepositorio.cs","qualifier":"FIL","path":"app/Repositorio/Interfaces/ISinistroRepositorio.cs","language":"cs","measures":[{"metric":"comment_lines_density","value":"0.0","bestValue":false},{"metric":"complexity","value":"0"},{"metric":"files","value":"1"},{"metric":"functions","value":"0"},{"metric":"ncloc","value":"12"},{"metric":"security_rating","value":"1.0","bestValue":true},{"metric":"duplicated_lines_density","value":"0.0","bestValue":true},{"metric":"test_failures","value":"0","bestValue":true},{"metric":"test_errors","value":"0","bestValue":true}]},{"id":"AYtQFh_ZlVtF5-wq_49d","key":"fga-eps-mds_2023.2-Dnit-UpsService:app/Services/Interfaces/ISinistroService.cs","name":"ISinistroService.cs","qualifier":"FIL","path":"app/Services/Interfaces/ISinistroService.cs","language":"cs","measures":[{"metric":"comment_lines_density","value":"0.0","bestValue":false},{"metric":"complexity","value":"0"},{"metric":"files","value":"1"},{"metric":"functions","value":"0"},{"metric":"ncloc","value":"12"},{"metric":"security_rating","value":"1.0","bestValue":true},{"metric":"duplicated_lines_density","value":"0.0","bestValue":true},{"metric":"test_failures","value":"0","bestValue":true},{"metric":"test_errors","value":"0","bestValue":true}]},{"id":"AYtQFh_ZlVtF5-wq_49c","key":"fga-eps-mds_2023.2-Dnit-UpsService:app/Services/Interfaces/IUpsService.cs","name":"IUpsService.cs","qualifier":"FIL","path":"app/Services/Interfaces/IUpsService.cs","language":"cs","measures":[{"metric":"comment_lines_density","value":"0.0","bestValue":false},{"metric":"complexity","value":"0"},{"metric":"files","value":"1"},{"metric":"functions","value":"0"},{"metric":"ncloc","value":"10"},{"metric":"security_rating","value":"1.0","bestValue":true},{"metric":"duplicated_lines_density","value":"0.0","bestValue":true},{"metric":"test_failures","value":"0","bestValue":true},{"metric":"test_errors","value":"0","bestValue":true}]},{"id":"AYpN5P0PgIp5pWdLoPuo","key":"fga-eps-mds_2023.2-Dnit-UpsService:app/Properties/launchSettings.json","name":"launchSettings.json","qualifier":"FIL","path":"app/Properties/launchSettings.json","language":"json","measures":[{"metric":"files","value":"1"},{"metric":"security_rating","value":"1.0","bestValue":true},{"metric":"duplicated_lines_density","value":"0.0","bestValue":true},{"metric":"test_failures","value":"0","bestValue":true},{"metric":"test_errors","value":"0","bestValue":true}]},{"id":"AYtQFh_ZlVtF5-wq_4-A","key":"fga-eps-mds_2023.2-Dnit-UpsService:api/ListaPaginada.cs","name":"ListaPaginada.cs","qualifier":"FIL","path":"api/ListaPaginada.cs","language":"cs","measures":[{"metric":"comment_lines_density","value":"0.0","bestValue":false},{"metric":"complexity","value":"11"},{"metric":"coverage","value":"100.0","bestValue":true},{"metric":"files","value":"1"},{"metric":"functions","value":"11"},{"metric":"ncloc","value":"19"},{"metric":"security_rating","value":"1.0","bestValue":true},{"metric":"duplicated_lines_density","value":"0.0","bestValue":true},{"metric":"test_failures","value":"0","bestValue":true},{"metric":"test_errors","value":"0","bestValue":true}]},{"id":"AYtQFh_ZlVtF5-wq_49-","key":"fga-eps-mds_2023.2-Dnit-UpsService:api/PesquisaSinistroFiltro.cs","name":"PesquisaSinistroFiltro.cs","qualifier":"FIL","path":"api/PesquisaSinistroFiltro.cs","language":"cs","measures":[{"metric":"comment_lines_density","value":"0.0","bestValue":false},{"metric":"complexity","value":"4"},{"metric":"coverage","value":"100.0","bestValue":true},{"metric":"files","value":"1"},{"metric":"functions","value":"4"},{"metric":"ncloc","value":"8"},{"metric":"security_rating","value":"1.0","bestValue":true},{"metric":"duplicated_lines_density","value":"0.0","bestValue":true},{"metric":"test_failures","value":"0","bestValue":true},{"metric":"test_errors","value":"0","bestValue":true}]},{"id":"AYpN5P0PgIp5pWdLoPup","key":"fga-eps-mds_2023.2-Dnit-UpsService:app/Properties","name":"Properties","qualifier":"DIR","path":"app/Properties","measures":[{"metric":"duplicated_lines_density","value":"0.0","bestValue":true},{"metric":"files","value":"1"},{"metric":"security_rating","value":"1.0","bestValue":true}]},{"id":"AYtQFh_ZlVtF5-wq_49u","key":"fga-eps-mds_2023.2-Dnit-UpsService:app/Repositorio","name":"Repositorio","qualifier":"DIR","path":"app/Repositorio","measures":[{"metric":"comment_lines_density","value":"0.0","bestValue":false},{"metric":"complexity","value":"6"},{"metric":"coverage","value":"100.0","bestValue":true},{"metric":"duplicated_lines_density","value":"0.0","bestValue":true},{"metric":"files","value":"4"},{"metric":"functions","value":"6"},{"metric":"ncloc","value":"115"},{"metric":"security_rating","value":"1.0","bestValue":true}]},{"id":"AYtQFh_ZlVtF5-wq_49n","key":"fga-eps-mds_2023.2-Dnit-UpsService:app/Entidades/Rodovia.cs","name":"Rodovia.cs","qualifier":"FIL","path":"app/Entidades/Rodovia.cs","language":"cs","measures":[{"metric":"comment_lines_density","value":"0.0","bestValue":false},{"metric":"complexity","value":"32"},{"metric":"coverage","value":"100.0","bestValue":true},{"metric":"files","value":"1"},{"metric":"functions","value":"32"},{"metric":"ncloc","value":"32"},{"metric":"security_rating","value":"1.0","bestValue":true},{"metric":"duplicated_lines_density","value":"0.0","bestValue":true},{"metric":"test_failures","value":"0","bestValue":true},{"metric":"test_errors","value":"0","bestValue":true}]},{"id":"AYpN5P0PgIp5pWdLoPul","key":"fga-eps-mds_2023.2-Dnit-UpsService:app/Controllers/RodoviaController.cs","name":"RodoviaController.cs","qualifier":"FIL","path":"app/Controllers/RodoviaController.cs","language":"cs","measures":[{"metric":"comment_lines_density","value":"0.0","bestValue":false},{"metric":"complexity","value":"6"},{"metric":"coverage","value":"90.9","bestValue":false},{"metric":"files","value":"1"},{"metric":"functions","value":"2"},{"metric":"ncloc","value":"56"},{"metric":"security_rating","value":"1.0","bestValue":true},{"metric":"duplicated_lines_density","value":"0.0","bestValue":true},{"metric":"test_failures","value":"0","bestValue":true},{"metric":"test_errors","value":"0","bestValue":true}]},{"id":"AYtQFh_ZlVtF5-wq_492","key":"fga-eps-mds_2023.2-Dnit-UpsService:test/RodoviaControllerTest.cs","name":"RodoviaControllerTest.cs","qualifier":"UTS","path":"test/RodoviaControllerTest.cs","language":"cs","measures":[{"metric":"security_rating","value":"1.0","bestValue":true},{"metric":"test_execution_time","value":"510"},{"metric":"tests","value":"5"},{"metric":"duplicated_lines_density","value":"0.0","bestValue":true},{"metric":"test_failures","value":"0","bestValue":true},{"metric":"test_errors","value":"0","bestValue":true}]},{"id":"AYtQFh_ZlVtF5-wq_49_","key":"fga-eps-mds_2023.2-Dnit-UpsService:api/RodoviaDTO.cs","name":"RodoviaDTO.cs","qualifier":"FIL","path":"api/RodoviaDTO.cs","language":"cs","measures":[{"metric":"comment_lines_density","value":"0.0","bestValue":false},{"metric":"complexity","value":"30"},{"metric":"coverage","value":"100.0","bestValue":true},{"metric":"files","value":"1"},{"metric":"functions","value":"30"},{"metric":"ncloc","value":"21"},{"metric":"security_rating","value":"1.0","bestValue":true},{"metric":"duplicated_lines_density","value":"0.0","bestValue":true},{"metric":"test_failures","value":"0","bestValue":true},{"metric":"test_errors","value":"0","bestValue":true}]},{"id":"AYtQFh_ZlVtF5-wq_49t","key":"fga-eps-mds_2023.2-Dnit-UpsService:app/Repositorio/RodoviaRepositorio.cs","name":"RodoviaRepositorio.cs","qualifier":"FIL","path":"app/Repositorio/RodoviaRepositorio.cs","language":"cs","measures":[{"metric":"comment_lines_density","value":"0.0","bestValue":false},{"metric":"complexity","value":"2"},{"metric":"coverage","value":"100.0","bestValue":true},{"metric":"files","value":"1"},{"metric":"functions","value":"2"},{"metric":"ncloc","value":"39"},{"metric":"security_rating","value":"1.0","bestValue":true},{"metric":"duplicated_lines_density","value":"0.0","bestValue":true},{"metric":"test_failures","value":"0","bestValue":true},{"metric":"test_errors","value":"0","bestValue":true}]},{"id":"AYtQFh_ZlVtF5-wq_49g","key":"fga-eps-mds_2023.2-Dnit-UpsService:app/Services/RodoviaService.cs","name":"RodoviaService.cs","qualifier":"FIL","path":"app/Services/RodoviaService.cs","language":"cs","measures":[{"metric":"comment_lines_density","value":"0.0","bestValue":false},{"metric":"complexity","value":"7"},{"metric":"coverage","value":"100.0","bestValue":true},{"metric":"files","value":"1"},{"metric":"functions","value":"3"},{"metric":"ncloc","value":"65"},{"metric":"security_rating","value":"1.0","bestValue":true},{"metric":"duplicated_lines_density","value":"0.0","bestValue":true},{"metric":"test_failures","value":"0","bestValue":true},{"metric":"test_errors","value":"0","bestValue":true}]},{"id":"AYpN5P0PgIp5pWdLoPu9","key":"fga-eps-mds_2023.2-Dnit-UpsService:test/RodoviaServiceTest.cs","name":"RodoviaServiceTest.cs","qualifier":"UTS","path":"test/RodoviaServiceTest.cs","language":"cs","measures":[{"metric":"security_rating","value":"1.0","bestValue":true},{"metric":"duplicated_lines_density","value":"0.0","bestValue":true},{"metric":"test_failures","value":"0","bestValue":true},{"metric":"test_errors","value":"0","bestValue":true}]},{"id":"AYpN5P0PgIp5pWdLoPu6","key":"fga-eps-mds_2023.2-Dnit-UpsService:test/Stub/RodoviaStub.cs","name":"RodoviaStub.cs","qualifier":"UTS","path":"test/Stub/RodoviaStub.cs","language":"cs","measures":[{"metric":"security_rating","value":"1.0","bestValue":true},{"metric":"duplicated_lines_density","value":"0.0","bestValue":true},{"metric":"test_failures","value":"0","bestValue":true},{"metric":"test_errors","value":"0","bestValue":true}]},{"id":"AYtQFh_ZlVtF5-wq_49k","key":"fga-eps-mds_2023.2-Dnit-UpsService:app/Services","name":"Services","qualifier":"DIR","path":"app/Services","measures":[{"metric":"comment_lines_density","value":"0.3","bestValue":false},{"metric":"complexity","value":"50"},{"metric":"coverage","value":"80.2","bestValue":false},{"metric":"duplicated_lines_density","value":"0.0","bestValue":true},{"metric":"files","value":"8"},{"metric":"functions","value":"28"},{"metric":"ncloc","value":"345"},{"metric":"security_rating","value":"1.0","bestValue":true}]},{"id":"AYtQFh_ZlVtF5-wq_49m","key":"fga-eps-mds_2023.2-Dnit-UpsService:app/Entidades/Sinistro.cs","name":"Sinistro.cs","qualifier":"FIL","path":"app/Entidades/Sinistro.cs","language":"cs","measures":[{"metric":"comment_lines_density","value":"0.0","bestValue":false},{"metric":"complexity","value":"39"},{"metric":"coverage","value":"97.1","bestValue":false},{"metric":"files","value":"1"},{"metric":"functions","value":"35"},{"metric":"ncloc","value":"64"},{"metric":"security_rating","value":"1.0","bestValue":true},{"metric":"duplicated_lines_density","value":"0.0","bestValue":true},{"metric":"test_failures","value":"0","bestValue":true},{"metric":"test_errors","value":"0","bestValue":true}]},{"id":"AYpN5P0PgIp5pWdLoPuk","key":"fga-eps-mds_2023.2-Dnit-UpsService:app/Controllers/SinistroController.cs","name":"SinistroController.cs","qualifier":"FIL","path":"app/Controllers/SinistroController.cs","language":"cs","measures":[{"metric":"comment_lines_density","value":"0.0","bestValue":false},{"metric":"complexity","value":"6"},{"metric":"coverage","value":"100.0","bestValue":true},{"metric":"files","value":"1"},{"metric":"functions","value":"2"},{"metric":"ncloc","value":"54"},{"metric":"security_rating","value":"1.0","bestValue":true},{"metric":"duplicated_lines_density","value":"0.0","bestValue":true},{"metric":"test_failures","value":"0","bestValue":true},{"metric":"test_errors","value":"0","bestValue":true}]},{"id":"AYtQFh_ZlVtF5-wq_496","key":"fga-eps-mds_2023.2-Dnit-UpsService:test/SinistroControllerTest.cs","name":"SinistroControllerTest.cs","qualifier":"UTS","path":"test/SinistroControllerTest.cs","language":"cs","measures":[{"metric":"security_rating","value":"1.0","bestValue":true},{"metric":"test_execution_time","value":"695"},{"metric":"tests","value":"5"},{"metric":"duplicated_lines_density","value":"0.0","bestValue":true},{"metric":"test_failures","value":"0","bestValue":true},{"metric":"test_errors","value":"0","bestValue":true}]},{"id":"AYtQFh_ZlVtF5-wq_498","key":"fga-eps-mds_2023.2-Dnit-UpsService:api/SinistroDTO.cs","name":"SinistroDTO.cs","qualifier":"FIL","path":"api/SinistroDTO.cs","language":"cs","measures":[{"metric":"comment_lines_density","value":"0.0","bestValue":false},{"metric":"complexity","value":"32"},{"metric":"coverage","value":"88.2","bestValue":false},{"metric":"files","value":"1"},{"metric":"functions","value":"32"},{"metric":"ncloc","value":"24"},{"metric":"security_rating","value":"1.0","bestValue":true},{"metric":"duplicated_lines_density","value":"0.0","bestValue":true},{"metric":"test_failures","value":"0","bestValue":true},{"metric":"test_errors","value":"0","bestValue":true}]},{"id":"AYtQFh_ZlVtF5-wq_49s","key":"fga-eps-mds_2023.2-Dnit-UpsService:app/Repositorio/SinistroRepositorio.cs","name":"SinistroRepositorio.cs","qualifier":"FIL","path":"app/Repositorio/SinistroRepositorio.cs","language":"cs","measures":[{"metric":"comment_lines_density","value":"0.0","bestValue":false},{"metric":"complexity","value":"4"},{"metric":"coverage","value":"100.0","bestValue":true},{"metric":"files","value":"1"},{"metric":"functions","value":"4"},{"metric":"ncloc","value":"55"},{"metric":"security_rating","value":"1.0","bestValue":true},{"metric":"duplicated_lines_density","value":"0.0","bestValue":true},{"metric":"test_failures","value":"0","bestValue":true},{"metric":"test_errors","value":"0","bestValue":true}]},{"id":"AYtQFh_ZlVtF5-wq_493","key":"fga-eps-mds_2023.2-Dnit-UpsService:test/SinistroRepositorioTest.cs","name":"SinistroRepositorioTest.cs","qualifier":"UTS","path":"test/SinistroRepositorioTest.cs","language":"cs","measures":[{"metric":"security_rating","value":"1.0","bestValue":true},{"metric":"test_execution_time","value":"571"},{"metric":"tests","value":"5"},{"metric":"duplicated_lines_density","value":"0.0","bestValue":true},{"metric":"test_failures","value":"0","bestValue":true},{"metric":"test_errors","value":"0","bestValue":true}]},{"id":"AYtQFh_ZlVtF5-wq_49i","key":"fga-eps-mds_2023.2-Dnit-UpsService:app/Services/SinistroService.cs","name":"SinistroService.cs","qualifier":"FIL","path":"app/Services/SinistroService.cs","language":"cs","measures":[{"metric":"comment_lines_density","value":"0.0","bestValue":false},{"metric":"complexity","value":"8"},{"metric":"coverage","value":"80.0","bestValue":false},{"metric":"files","value":"1"},{"metric":"functions","value":"4"},{"metric":"ncloc","value":"94"},{"metric":"security_rating","value":"1.0","bestValue":true},{"metric":"duplicated_lines_density","value":"0.0","bestValue":true},{"metric":"test_failures","value":"0","bestValue":true},{"metric":"test_errors","value":"0","bestValue":true}]},{"id":"AYpN5P0PgIp5pWdLoPu_","key":"fga-eps-mds_2023.2-Dnit-UpsService:test/SinistroServiceTest.cs","name":"SinistroServiceTest.cs","qualifier":"UTS","path":"test/SinistroServiceTest.cs","language":"cs","measures":[{"metric":"security_rating","value":"1.0","bestValue":true},{"metric":"duplicated_lines_density","value":"0.0","bestValue":true},{"metric":"test_failures","value":"0","bestValue":true},{"metric":"test_errors","value":"0","bestValue":true}]},{"id":"AYpN5P0PgIp5pWdLoPu5","key":"fga-eps-mds_2023.2-Dnit-UpsService:test/Stub/SinistroStub.cs","name":"SinistroStub.cs","qualifier":"UTS","path":"test/Stub/SinistroStub.cs","language":"cs","measures":[{"metric":"security_rating","value":"1.0","bestValue":true},{"metric":"duplicated_lines_density","value":"0.0","bestValue":true},{"metric":"test_failures","value":"0","bestValue":true},{"metric":"test_errors","value":"0","bestValue":true}]},{"id":"AYpN5P0PgIp5pWdLoPu-","key":"fga-eps-mds_2023.2-Dnit-UpsService:test/SinistroTest.cs","name":"SinistroTest.cs","qualifier":"UTS","path":"test/SinistroTest.cs","language":"cs","measures":[{"metric":"security_rating","value":"1.0","bestValue":true},{"metric":"test_execution_time","value":"1"},{"metric":"tests","value":"4"},{"metric":"duplicated_lines_density","value":"0.0","bestValue":true},{"metric":"test_failures","value":"0","bestValue":true},{"metric":"test_errors","value":"0","bestValue":true}]},{"id":"AYpN5P0PgIp5pWdLoPu7","key":"fga-eps-mds_2023.2-Dnit-UpsService:test/Stub","name":"Stub","qualifier":"DIR","path":"test/Stub","measures":[{"metric":"security_rating","value":"1.0","bestValue":true}]},{"id":"AYpN5P0PgIp5pWdLoPvB","key":"fga-eps-mds_2023.2-Dnit-UpsService:test","name":"test","qualifier":"DIR","path":"test","measures":[{"metric":"security_rating","value":"1.0","bestValue":true},{"metric":"test_errors","value":"0","bestValue":true},{"metric":"test_execution_time","value":"2526"},{"metric":"test_failures","value":"0","bestValue":true},{"metric":"tests","value":"25"}]},{"id":"AYpN5P0PgIp5pWdLoPuj","key":"fga-eps-mds_2023.2-Dnit-UpsService:app/Controllers/UpsController.cs","name":"UpsController.cs","qualifier":"FIL","path":"app/Controllers/UpsController.cs","language":"cs","measures":[{"metric":"comment_lines_density","value":"0.0","bestValue":false},{"metric":"complexity","value":"4"},{"metric":"coverage","value":"100.0","bestValue":true},{"metric":"files","value":"1"},{"metric":"functions","value":"3"},{"metric":"ncloc","value":"40"},{"metric":"security_rating","value":"1.0","bestValue":true},{"metric":"duplicated_lines_density","value":"0.0","bestValue":true},{"metric":"test_failures","value":"0","bestValue":true},{"metric":"test_errors","value":"0","bestValue":true}]},{"id":"AYtQFh_ZlVtF5-wq_497","key":"fga-eps-mds_2023.2-Dnit-UpsService:test/UpsControllerTest.cs","name":"UpsControllerTest.cs","qualifier":"UTS","path":"test/UpsControllerTest.cs","language":"cs","measures":[{"metric":"security_rating","value":"1.0","bestValue":true},{"metric":"test_execution_time","value":"746"},{"metric":"tests","value":"4"},{"metric":"duplicated_lines_density","value":"0.0","bestValue":true},{"metric":"test_failures","value":"0","bestValue":true},{"metric":"test_errors","value":"0","bestValue":true}]},{"id":"AYtQFh_ZlVtF5-wq_49y","key":"fga-eps-mds_2023.2-Dnit-UpsService:app/Dominio/UpsDetalhado.cs","name":"UpsDetalhado.cs","qualifier":"FIL","path":"app/Dominio/UpsDetalhado.cs","language":"cs","measures":[{"metric":"comment_lines_density","value":"0.0","bestValue":false},{"metric":"complexity","value":"13"},{"metric":"coverage","value":"100.0","bestValue":true},{"metric":"files","value":"1"},{"metric":"functions","value":"13"},{"metric":"ncloc","value":"16"},{"metric":"security_rating","value":"1.0","bestValue":true},{"metric":"duplicated_lines_density","value":"0.0","bestValue":true},{"metric":"test_failures","value":"0","bestValue":true},{"metric":"test_errors","value":"0","bestValue":true}]},{"id":"AYtQFh_ZlVtF5-wq_49j","key":"fga-eps-mds_2023.2-Dnit-UpsService:app/Services/UpsService.cs","name":"UpsService.cs","qualifier":"FIL","path":"app/Services/UpsService.cs","language":"cs","measures":[{"metric":"comment_lines_density","value":"1.3","bestValue":false},{"metric":"complexity","value":"11"},{"metric":"coverage","value":"100.0","bestValue":true},{"metric":"files","value":"1"},{"metric":"functions","value":"5"},{"metric":"ncloc","value":"75"},{"metric":"security_rating","value":"1.0","bestValue":true},{"metric":"duplicated_lines_density","value":"0.0","bestValue":true},{"metric":"test_failures","value":"0","bestValue":true},{"metric":"test_errors","value":"0","bestValue":true}]},{"id":"AYpN5P0PgIp5pWdLoPvA","key":"fga-eps-mds_2023.2-Dnit-UpsService:test/UpsServiceTest.cs","name":"UpsServiceTest.cs","qualifier":"UTS","path":"test/UpsServiceTest.cs","language":"cs","measures":[{"metric":"security_rating","value":"1.0","bestValue":true},{"metric":"test_execution_time","value":"3"},{"metric":"tests","value":"2"},{"metric":"duplicated_lines_density","value":"0.0","bestValue":true},{"metric":"test_failures","value":"0","bestValue":true},{"metric":"test_errors","value":"0","bestValue":true}]},{"id":"AYpN5P0PgIp5pWdLoPu8","key":"fga-eps-mds_2023.2-Dnit-UpsService:test/Usings.cs","name":"Usings.cs","qualifier":"UTS","path":"test/Usings.cs","language":"cs","measures":[{"metric":"security_rating","value":"1.0","bestValue":true},{"metric":"duplicated_lines_density","value":"0.0","bestValue":true},{"metric":"test_failures","value":"0","bestValue":true},{"metric":"test_errors","value":"0","bestValue":true}]},{"id":"AYtQFh_ZlVtF5-wq_490","key":"fga-eps-mds_2023.2-Dnit-UpsService:test/Stub/UtilsExtensions.cs","name":"UtilsExtensions.cs","qualifier":"UTS","path":"test/Stub/UtilsExtensions.cs","language":"cs","measures":[{"metric":"security_rating","value":"1.0","bestValue":true},{"metric":"duplicated_lines_density","value":"0.0","bestValue":true},{"metric":"test_failures","value":"0","bestValue":true},{"metric":"test_errors","value":"0","bestValue":true}]}]}